hrshit/__init__.py
hrshit/art.py
hrshit/player.py
hrshit-8.2.2004.dist-info/METADATA
hrshit-8.2.2004.dist-info/WHEEL
hrshit-8.2.2004.dist-info/entry_points.txt
hrshit-8.2.2004.dist-info/top_level.txt
hrshit-8.2.2004.dist-info/RECORD
