Metadata-Version: 2.1
Name: hrshit
Version: 8.2.2004
Summary: package for playing pikmin from the cli.
Home-page: https://github.com/arpy8/hrshit
Author: Masti Khor
Author-email: arpitsengar99@gmail.com
Classifier: Programming Language :: Python :: 3
Classifier: License :: OSI Approved :: MIT License
Classifier: Operating System :: OS Independent
